traffic_light/traffic.v
module traffic (CURR, NSC, EWC, NEXT);

	input CURR, NSC, EWC;
	output NEXT; 

	assign NEXT = ~CURR & EWC | ~NSC & EWC;

endmodule

traffic_light/traffic_tb.v
`timescale 1ns / 1ns
`include "traffic.v"

module traffic_tb;

reg CURR, NSC, EWC;
wire NEXT;

traffic uut(CURR, NSC, EWC, NEXT);

initial begin
	
	$dumpfile("traffic_tb.vcd");
	$dumpvars(0, traffic_tb);
	
	{CURR, NSC, EWC} = 3'd0;	#20;
	{CURR, NSC, EWC} = 3'd1;	#20;
	{CURR, NSC, EWC} = 3'd2;	#20;
	{CURR, NSC, EWC} = 3'd3;	#20;
	{CURR, NSC, EWC} = 3'd4;	#20;
	{CURR, NSC, EWC} = 3'd5;	#20;
	{CURR, NSC, EWC} = 3'd6;	#20;
	{CURR, NSC, EWC} = 3'd7;	#20;
	
	$display("Test complete");

end

endmodule

traffic_light/traffic_tb.vcd
$date
	Sun Oct 16 19:19:46 2022
$end
$version
	Icarus Verilog
$end
$timescale
	1ns
$end
$scope module traffic_tb $end
$var wire 1 ! NEXT $end
$var reg 1 " CURR $end
$var reg 1 # EWC $end
$var reg 1 $ NSC $end
$scope module uut $end
$var wire 1 " CURR $end
$var wire 1 # EWC $end
$var wire 1 ! NEXT $end
$var wire 1 $ NSC $end
$upscope $end
$upscope $end
$enddefinitions $end
$comment Show the parameter values. $end
$dumpall
$end
#0
$dumpvars
0$
0#
0"
0!
$end
#20
1!
1#
#40
0!
1$
0#
#60
1!
1#
#80
0!
1"
0$
0#
#100
1!
1#
#120
0!
1$
0#
#140
1#
